instant_client/__init__.py
instant_client/instant_client.py
instant_client/version.py
instant_client-0.0.1.dist-info/LICENSE.txt
instant_client-0.0.1.dist-info/METADATA
instant_client-0.0.1.dist-info/WHEEL
instant_client-0.0.1.dist-info/top_level.txt
instant_client-0.0.1.dist-info/RECORD
