Metadata-Version: 2.1
Name: instant-client
Version: 0.0.1
Summary: Type safe JSON RPC client with automatic (de)serialization. Best paired with instant_api.
Home-page: http://github.com/alexmojaki/instant_client
Author: Alex Hall
Author-email: alex.mojaki@gmail.com
License: MIT
Platform: UNKNOWN
Classifier: Intended Audience :: Developers
Classifier: Programming Language :: Python :: 3
Classifier: Programming Language :: Python :: 3.7
Classifier: Programming Language :: Python :: 3.8
Classifier: License :: OSI Approved :: MIT License
Classifier: Operating System :: OS Independent
Requires-Dist: jsonrpcclient
Requires-Dist: datafunctions
Provides-Extra: requests
Requires-Dist: requests ; extra == 'requests'
Provides-Extra: tests
Requires-Dist: pytest ; extra == 'tests'
Requires-Dist: instant-api ; extra == 'tests'
Requires-Dist: flask ; extra == 'tests'
Requires-Dist: requests ; extra == 'tests'
